lp_analyzer/__init__.py
lp_analyzer/__main__.py
lp_analyzer/analyze.py
lp_analyzer/core.py
lp_analyzer/reader.py
lp_analyzer/util.py
lp_analyzer/tests/__init__.py
lp_analyzer/tests/test_analyze.py
lp_analyzer-1.2.1.dist-info/LICENSE
lp_analyzer-1.2.1.dist-info/METADATA
lp_analyzer-1.2.1.dist-info/WHEEL
lp_analyzer-1.2.1.dist-info/entry_points.txt
lp_analyzer-1.2.1.dist-info/top_level.txt
lp_analyzer-1.2.1.dist-info/RECORD
