Metadata-Version: 2.1
Name: lp-analyzer
Version: 1.2.1
Summary: Analyze numerical issues in linear programs
Author-email: Martin Staadecker <machstg@gmail.com>
License: MIT License
Project-URL: Homepage, https://github.com/staadecker/lp-analyzer
Keywords: linear programming,numerical issues
Classifier: License :: OSI Approved :: MIT License
Classifier: Programming Language :: Python
Classifier: Programming Language :: Python :: 3
Requires-Python: >=3.7
License-File: LICENSE
Requires-Dist: tabulate
Provides-Extra: dev
Requires-Dist: black[d] ; extra == 'dev'
Requires-Dist: pytest ; extra == 'dev'
Requires-Dist: build ; extra == 'dev'
Requires-Dist: twine ; extra == 'dev'
